yucebio_notifier/__init__.py
yucebio_notifier/commands.py
yucebio_notifier/backend/__init__.py
yucebio_notifier/backend/base.py
yucebio_notifier/backend/dingding.py
yucebio_notifier/utils/__init__.py
yucebio_notifier/utils/markdown.py
Yucebio_Notifier-0.0.3.dist-info/METADATA
Yucebio_Notifier-0.0.3.dist-info/WHEEL
Yucebio_Notifier-0.0.3.dist-info/entry_points.txt
Yucebio_Notifier-0.0.3.dist-info/top_level.txt
Yucebio_Notifier-0.0.3.dist-info/RECORD
