Metadata-Version: 2.1
Name: Yucebio-Notifier
Version: 0.0.3
Summary: 通用钉钉消息推送工具
Home-page: UNKNOWN
Author: huangqingjun
Author-email: huangqingjun@yucebio.com
License: MIT
Platform: UNKNOWN
Classifier: License :: OSI Approved :: MIT License
Classifier: Programming Language :: Python
Classifier: Programming Language :: Python :: 3
Classifier: Programming Language :: Python :: 3.8
Classifier: Programming Language :: Python :: Implementation :: CPython
Classifier: Programming Language :: Python :: Implementation :: PyPy
Requires-Python: >=3.8
Requires-Dist: click
Requires-Dist: icecream
Requires-Dist: alibabacloud-dingtalk
Requires-Dist: Yucebio-Config
